zote4o2_test/__init__.py
zote4o2_test/calc.py
zote4o2_test-0.1.0.dist-info/METADATA
zote4o2_test-0.1.0.dist-info/WHEEL
zote4o2_test-0.1.0.dist-info/top_level.txt
zote4o2_test-0.1.0.dist-info/RECORD
