Metadata-Version: 2.1
Name: zote4o2-test
Version: 0.1.0
Summary: Demo library
Home-page: https://zote4o2_test.readthedocs.io/
Author: John Doe
Author-email: example@email.com
License: MIT
Platform: UNKNOWN
Classifier: Intended Audience :: Developers
Classifier: License :: OSI Approved :: MIT License
Classifier: Programming Language :: Python
Classifier: Programming Language :: Python :: 3
Classifier: Programming Language :: Python :: 3.10
Classifier: Operating System :: OS Independent
Requires-Dist: numpy
